markdown_to_presentation.py
markdown_to_presentation-0.0.34.dist-info/LICENSE
markdown_to_presentation-0.0.34.dist-info/METADATA
markdown_to_presentation-0.0.34.dist-info/WHEEL
markdown_to_presentation-0.0.34.dist-info/entry_points.txt
markdown_to_presentation-0.0.34.dist-info/top_level.txt
markdown_to_presentation-0.0.34.dist-info/RECORD
