Metadata-Version: 2.1
Name: markdown-to-presentation
Version: 0.0.34
Summary: Takes markdown and turns it into an html slideshow.
Home-page: https://github.com/anthonywritescode/markdown-to-presentation
Author: Anthony Sottile
Author-email: asottile@umich.edu
License: MIT
Classifier: License :: OSI Approved :: MIT License
Classifier: Programming Language :: Python :: 3
Classifier: Programming Language :: Python :: 3 :: Only
Requires-Python: >=3.8
License-File: LICENSE
Requires-Dist: libsass (>=0.16.1)
Requires-Dist: markdown-code-blocks (>=3.0.0)
